mopidy_api_explorer/__init__.py
mopidy_api_explorer/ext.conf
mopidy_api_explorer/static/index.html
mopidy_api_explorer/static/css/app.css
mopidy_api_explorer/static/css/vendor/bootstrap-v5.0.0-beta1.min.css
mopidy_api_explorer/static/css/vendor/bootstrap-v5.0.0-beta1.min.css.map
mopidy_api_explorer/static/js/app.js
mopidy_api_explorer/static/js/vendor/bootstrap-v5.0.0-beta1.min.js
mopidy_api_explorer/static/js/vendor/bootstrap-v5.0.0-beta1.min.js.map
mopidy_api_explorer/static/js/vendor/handlebars-v4.7.6.min.js
mopidy_api_explorer/static/js/vendor/mopidy-v1.2.1.min.js
mopidy_api_explorer/static/js/vendor/mopidy-v1.2.1.min.js.map
mopidy_api_explorer-2.0.0a1.dist-info/licenses/LICENSE
mopidy_api_explorer-2.0.0a1.dist-info/METADATA
mopidy_api_explorer-2.0.0a1.dist-info/WHEEL
mopidy_api_explorer-2.0.0a1.dist-info/entry_points.txt
mopidy_api_explorer-2.0.0a1.dist-info/top_level.txt
mopidy_api_explorer-2.0.0a1.dist-info/RECORD
