Metadata-Version: 2.4
Name: mopidy-api-explorer
Version: 2.0.0a1
Summary: Mopidy extension which lets you explore the JSON-RPC API
Author-email: Matthew Gamble <git@matthewgamble.net>
License: MIT
Project-URL: Homepage, https://github.com/mopidy/mopidy-api-explorer
Classifier: Environment :: No Input/Output (Daemon)
Classifier: Intended Audience :: End Users/Desktop
Classifier: License :: OSI Approved :: MIT License
Classifier: Operating System :: OS Independent
Classifier: Topic :: Multimedia :: Sound/Audio :: Players
Requires-Python: >=3.13
License-File: LICENSE
Requires-Dist: mopidy>=4.0.0a12
Requires-Dist: pykka>=4.1
Dynamic: license-file
